idmaths/__init__.py
idmaths/champernowne.py
idmaths/copelanderdos.py
idmaths/thuemorse.py
idmaths-0.5.dist-info/LICENCE
idmaths-0.5.dist-info/METADATA
idmaths-0.5.dist-info/WHEEL
idmaths-0.5.dist-info/top_level.txt
idmaths-0.5.dist-info/RECORD
