Metadata-Version: 2.1
Name: idmaths
Version: 0.5
Summary: Useful mathematics modules
Home-page: https://github.com/ivandebono/idmaths
Author: Ivan Debono
Author-email: mail@ivandebono.eu
License: UNKNOWN
Platform: UNKNOWN
Classifier: Programming Language :: Python :: 3
Classifier: License :: OSI Approved :: MIT License
Classifier: Operating System :: OS Independent
Requires-Python: >=3.6
